ddtcv/__init__.py
ddtcv/abstract.py
ddtcv/angle.py
ddtcv/onnx.py
ddtcv/static/model/angle_1_rec_en_number_lite/angle_1_rec_en_number_lite.onnx
ddtcv/static/model/angle_1_rec_en_number_lite/angle_dict.txt
ddtcv/static/model/wind_1_rec_en_number_lite/wind_1_rec_en_number_lite.onnx
ddtcv/static/model/wind_1_rec_en_number_lite/wind_dict.txt
ddtcv/tests/__init__.py
ddtcv/tests/image/img.png
ddtcv/tests/image/img2.png
ddtcv/tests/image/img2_wind.png
ddtcv/tests/test_angle.py
ddtcv/tests/test_onnx.py
ddtcv/tests/test_wind.py
ddtcv/tools/load_model.py
ddtcv/tools/postprocess.py
ddtcv/tools/preprocess.py
ddtcv/wind.py
ddtcv-0.1.3.dist-info/WHEEL
ddtcv-0.1.3.dist-info/METADATA
ddtcv-0.1.3.dist-info/RECORD
