Metadata-Version: 2.1
Name: ddtcv
Version: 0.1.3
Summary: DDT CV.
License: MIT
Author: TsangHans
Author-email: gzzenghan@189.cn
Requires-Python: >=3.7,<4.0
Classifier: License :: OSI Approved :: MIT License
Classifier: Programming Language :: Python :: 3
Classifier: Programming Language :: Python :: 3.7
Classifier: Programming Language :: Python :: 3.8
Classifier: Programming Language :: Python :: 3.9
Classifier: Programming Language :: Python :: 3.10
Classifier: Programming Language :: Python :: 3.11
Requires-Dist: numpy (>=1.21.6,<2.0.0)
Requires-Dist: onnxruntime (>=1.13.1,<2.0.0)
Requires-Dist: opencv-python (>=4.4.0.46,<5.0.0.0)
